aliyunsdkmns_open/__init__.py
aliyunsdkmns_open/endpoint.py
aliyunsdkmns_open/request/__init__.py
aliyunsdkmns_open/request/v20220119/CreateQueueRequest.py
aliyunsdkmns_open/request/v20220119/CreateTopicRequest.py
aliyunsdkmns_open/request/v20220119/DeleteQueueRequest.py
aliyunsdkmns_open/request/v20220119/DeleteTopicRequest.py
aliyunsdkmns_open/request/v20220119/GetQueueAttributesRequest.py
aliyunsdkmns_open/request/v20220119/GetSubscriptionAttributesRequest.py
aliyunsdkmns_open/request/v20220119/GetTopicAttributesRequest.py
aliyunsdkmns_open/request/v20220119/ListQueueRequest.py
aliyunsdkmns_open/request/v20220119/ListSubscriptionByTopicRequest.py
aliyunsdkmns_open/request/v20220119/ListTopicRequest.py
aliyunsdkmns_open/request/v20220119/SetQueueAttributesRequest.py
aliyunsdkmns_open/request/v20220119/SetSubscriptionAttributesRequest.py
aliyunsdkmns_open/request/v20220119/SetTopicAttributesRequest.py
aliyunsdkmns_open/request/v20220119/SubscribeRequest.py
aliyunsdkmns_open/request/v20220119/UnsubscribeRequest.py
aliyunsdkmns_open/request/v20220119/__init__.py
aliyun_python_sdk_mns_open-1.0.2.dist-info/LICENSE
aliyun_python_sdk_mns_open-1.0.2.dist-info/METADATA
aliyun_python_sdk_mns_open-1.0.2.dist-info/WHEEL
aliyun_python_sdk_mns_open-1.0.2.dist-info/top_level.txt
aliyun_python_sdk_mns_open-1.0.2.dist-info/RECORD
